happydoc/__init__.py
happydoc/cli.py
happydoc/document.py
happydoc/samples/devis.md
happydoc/samples/report.md
happydoc/styles/happydev.css
happydoc/styles/logo_HD_generique.png
happydoc-0.1.1.dist-info/LICENSE
happydoc-0.1.1.dist-info/METADATA
happydoc-0.1.1.dist-info/WHEEL
happydoc-0.1.1.dist-info/entry_points.txt
happydoc-0.1.1.dist-info/top_level.txt
happydoc-0.1.1.dist-info/RECORD
